qc_utils/__init__.py
qc_utils/parsers.py
qc_utils/qcmetric.py
qc_utils/test/__init__.py
qc_utils/test/test_parsers.py
qc_utils/test/test_qcmetric.py
qc_utils-20.9.1.dist-info/LICENSE
qc_utils-20.9.1.dist-info/METADATA
qc_utils-20.9.1.dist-info/WHEEL
qc_utils-20.9.1.dist-info/top_level.txt
qc_utils-20.9.1.dist-info/RECORD
